{
  "total": 5,
  "recommendations": [
    {
      "code": "7203.T",
      "name": "Toyota Motor Corporation",
      "currentPrice": 2724.5,
      "previousClose": 2696.5,
      "predictedPrice": 3196.5,
      "changePercent": 1.0103838308918969,
      "recommendation": "HOLD",
      "score": 40,
      "predictedProfitMargin": 0.5410726849526255
    },
    {
      "code": "8306.T",
      "name": "Mitsubishi UFJ Financial Group, Inc.",
      "currentPrice": 2127.0,
      "previousClose": 2110.5,
      "predictedPrice": 2610.5,
      "changePercent": 1.007818052594172,
      "recommendation": "BUY",
      "score": 100,
      "predictedProfitMargin": 0.829003791084043
    },
    {
      "code": "6501.T",
      "name": "Hitachi, Ltd.",
      "currentPrice": 4283.0,
      "previousClose": 4697.0,
      "predictedPrice": 5197.0,
      "changePercent": 0.9118586331701086,
      "recommendation": "BUY",
      "score": 100,
      "predictedProfitMargin": 0.1292730767172573
    },
    {
      "code": "6758.T",
      "name": "Sony Group Corporation",
      "currentPrice": 3680.0,
      "previousClose": 3682.0,
      "predictedPrice": 4182.0,
      "changePercent": 0.9994568169473113,
      "recommendation": "BUY",
      "score": 71,
      "predictedProfitMargin": 0.427286663452612
    },
    {
      "code": "6861.T",
      "name": "Keyence Corporation",
      "currentPrice": 56830.0,
      "previousClose": 55200.0,
      "predictedPrice": 55700.0,
      "changePercent": 1.0295289855072465,
      "recommendation": "HOLD",
      "score": 59,
      "predictedProfitMargin": 0.5940965809513369
    }
  ],
  "stats": {
    "buy": 3,
    "hold": 2,
    "sell": 0,
    "avgGain": 0.8265077198517892
  }
}